magicode/__init__.py
magicode/main.py
magicode-0.0.5.dist-info/LICENSE
magicode-0.0.5.dist-info/METADATA
magicode-0.0.5.dist-info/WHEEL
magicode-0.0.5.dist-info/entry_points.txt
magicode-0.0.5.dist-info/top_level.txt
magicode-0.0.5.dist-info/RECORD
