Metadata-Version: 2.1
Name: magicode
Version: 0.0.5
Summary: The CLI for Magicode.
Author-email: MagiCode <hello@magicode.ai>
License: LGPL-3.0-or-later
Project-URL: Homepage, https://www.magicode.ai
Classifier: Programming Language :: Python :: 3
Classifier: Operating System :: OS Independent
Classifier: License :: OSI Approved :: GNU Lesser General Public License v3 (LGPLv3)
Requires-Python: >=3.8
License-File: LICENSE
Requires-Dist: click
Requires-Dist: keyring
Requires-Dist: requests
Requires-Dist: tqdm
